{
  "project_name": "MyPkg",
  "project_slug": "mypkg",
  "dir_name": "mypkg",
  "description": "Short description of the project.",
  "author": "Johan Larsson",
  "email": "johan@jolars.co",
  "year": "{% now 'utc', '%Y' %}",
  "orcid": "0000-0002-4029-5945",
  "gh_user": "jolars",
  "gh_repo": "mypkg",
  "license": [
    "MIT",
    "GNU GPL v3.0",
    "BSD-3",
    "Apache Software License 2.0"
  ],
  "_copy_without_render": [
    "*.pdf",
    "*.so",
    "*.o",
    "*.png",
    "*.jpg",
    "*.svg",
    "*.rst",
    ".github/workflows/*"
  ],
  "_extensions": [
    "jinja2_time.TimeExtension"
  ]
}
